Guias/Guia_09/Clock.v
// ------------------------- 
// Clock.v
// Clock Generator
// Nome: Daniel Matos Marques
// Matricula: 800712
// ------------------------- 

module clock ( output clk ); 
    reg clk;
    
    initial begin : start
    clk = 1'b0; 
    end // start

    always begin : clock 
        #12 clk = ~clk; 
    end // clock
endmodule // clock ( )

Guias/Guia_09/Guia_0906.v
// ------------------------- 
// Guia_0906.v
// Test Clock Generator (7) 
// Nome: Daniel Matos Marques
// Matricula: 800712
// ------------------------- 

`include "clock.v" 

module pulse1 ( signal, clock ); 
    input  clock; 
    output signal; 
    reg    signal; 
    
    always @ ( negedge clock ) 
    begin : pulse
        #21  signal = 1'b1;
        #3  signal = 1'b0;            
        #21  signal = 1'b1;
        #3  signal = 1'b0;            
        #21  signal = 1'b1;
        #3  signal = 1'b0;            
    end // end pulse
endmodule // pulse ( )

module Guia_0906; 
    wire  clock; 
    clock clk ( clock ); 
    
    wire  p1; 
    pulse1 pls1 ( p1, clock ); 
    
    initial begin : main 
        $dumpfile ( "Guia_0906.vcd" ); 
        $dumpvars ( 1, clock, p1 ); 
        
        #480 $finish; 
    end // main
endmodule // Guia_0906 ( )

Guias/Guia_09/Guia_0906.vcd
$date
	Sun Apr 13 17:23:10 2025
$end
$version
	Icarus Verilog
$end
$timescale
	1s
$end
$scope module Guia_0906 $end
$var wire 1 ! clock $end
$upscope $end
$scope module Guia_0906 $end
$var wire 1 " p1 $end
$upscope $end
$enddefinitions $end
$comment Show the parameter values. $end
$dumpall
$end
#0
$dumpvars
x"
0!
$end
#12
1!
#24
0!
#36
1!
#45
1"
#48
0"
0!
#60
1!
#69
1"
#72
0"
0!
#84
1!
#93
1"
#96
0"
0!
#108
1!
#120
0!
#132
1!
#141
1"
#144
0"
0!
#156
1!
#165
1"
#168
0"
0!
#180
1!
#189
1"
#192
0"
0!
#204
1!
#216
0!
#228
1!
#237
1"
#240
0"
0!
#252
1!
#261
1"
#264
0"
0!
#276
1!
#285
1"
#288
0"
0!
#300
1!
#312
0!
#324
1!
#333
1"
#336
0"
0!
#348
1!
#357
1"
#360
0"
0!
#372
1!
#381
1"
#384
0"
0!
#396
1!
#408
0!
#420
1!
#429
1"
#432
0"
0!
#444
1!
#453
1"
#456
0"
0!
#468
1!
#477
1"
#480
0"
0!