Guias/Guia_09/Clock.v
// ------------------------- 
// Clock.v
// Clock Generator
// Nome: Daniel Matos Marques
// Matricula: 800712
// ------------------------- 

module clock ( output clk ); 
    reg clk;
    
    initial begin : start
    clk = 1'b0; 
    end // start

    always begin : clock 
        #12 clk = ~clk; 
    end // clock
endmodule // clock ( )

Guias/Guia_09/Guia_0904.v
// ------------------------- 
// Guia_0904.v
// Test Clock Generator (5) 
// Nome: Daniel Matos Marques
// Matricula: 800712
// ------------------------- 

`include "clock.v" 

module pulse ( signal, clock ); 
    input  clock; 
    output signal; 
    reg    signal; 
    
    always @ ( clock ) 
    begin : pulse
            signal = 1'b1;
        #4  signal = 1'b0;
        #4  signal = 1'b1;
        #4  signal = 1'b0;  
        #4  signal = 1'b1;
        #4  signal = 1'b0;  
    end // end pulse
endmodule // pulse ( )

module Guia_0904; 
    wire  clock; 
    clock clk ( clock ); 
    
    wire  p1; 
    pulse pls1 ( p1, clock ); 
    
    initial begin : main 
        $dumpfile ( "Guia_0904.vcd" ); 
        $dumpvars ( 1, clock, p1 ); 
        
        #480 $finish; 
    end // main
endmodule // Guia_0904 ( )

Guias/Guia_09/Guia_0904.vcd
$date
	Sun Apr 13 16:36:43 2025
$end
$version
	Icarus Verilog
$end
$timescale
	1s
$end
$scope module Guia_0904 $end
$var wire 1 ! clock $end
$upscope $end
$scope module Guia_0904 $end
$var wire 1 " p1 $end
$upscope $end
$enddefinitions $end
$comment Show the parameter values. $end
$dumpall
$end
#0
$dumpvars
1"
0!
$end
#4
0"
#8
1"
#12
0"
1!
#16
1"
#20
0"
#24
1"
0!
#28
0"
#32
1"
#36
0"
1!
#40
1"
#44
0"
#48
1"
0!
#52
0"
#56
1"
#60
0"
1!
#64
1"
#68
0"
#72
1"
0!
#76
0"
#80
1"
#84
0"
1!
#88
1"
#92
0"
#96
1"
0!
#100
0"
#104
1"
#108
0"
1!
#112
1"
#116
0"
#120
1"
0!
#124
0"
#128
1"
#132
0"
1!
#136
1"
#140
0"
#144
1"
0!
#148
0"
#152
1"
#156
0"
1!
#160
1"
#164
0"
#168
1"
0!
#172
0"
#176
1"
#180
0"
1!
#184
1"
#188
0"
#192
1"
0!
#196
0"
#200
1"
#204
0"
1!
#208
1"
#212
0"
#216
1"
0!
#220
0"
#224
1"
#228
0"
1!
#232
1"
#236
0"
#240
1"
0!
#244
0"
#248
1"
#252
0"
1!
#256
1"
#260
0"
#264
1"
0!
#268
0"
#272
1"
#276
0"
1!
#280
1"
#284
0"
#288
1"
0!
#292
0"
#296
1"
#300
0"
1!
#304
1"
#308
0"
#312
1"
0!
#316
0"
#320
1"
#324
0"
1!
#328
1"
#332
0"
#336
1"
0!
#340
0"
#344
1"
#348
0"
1!
#352
1"
#356
0"
#360
1"
0!
#364
0"
#368
1"
#372
0"
1!
#376
1"
#380
0"
#384
1"
0!
#388
0"
#392
1"
#396
0"
1!
#400
1"
#404
0"
#408
1"
0!
#412
0"
#416
1"
#420
0"
1!
#424
1"
#428
0"
#432
1"
0!
#436
0"
#440
1"
#444
0"
1!
#448
1"
#452
0"
#456
1"
0!
#460
0"
#464
1"
#468
0"
1!
#472
1"
#476
0"
#480
1"
0!